Metadata-Version: 2.1
Name: where-i-went
Version: 0.1.4
